polymind/__init__.py
polymind-0.1.0.dist-info/LICENSE
polymind-0.1.0.dist-info/METADATA
polymind-0.1.0.dist-info/WHEEL
polymind-0.1.0.dist-info/RECORD
