Metadata-Version: 2.1
Name: polymind
Version: 0.1.0
Summary: PolyMind is a customizable collaborative multi-agent framework for collective intelligence and distributed problem solving.
License: MIT
Author: Yx Jiang
Author-email: 2237303+yxjiang@users.noreply.github.com
Requires-Python: >=3.10,<4.0
Classifier: License :: OSI Approved :: MIT License
Classifier: Programming Language :: Python :: 3
Classifier: Programming Language :: Python :: 3.10
Classifier: Programming Language :: Python :: 3.11
